Workbook

Sheet aufgaben
A1: ANWENDUNG VON FUNKTIONEN
A3: 3.1 Grundrechen- und Statistikfunktionen
A5: Gesamtumsatz aller Verkäufe: | B5: =SUM(verkaeufe!G2:G27) -> 21955 | C5: SUMME
A7: Durchschnittlicher Umsatz: | B7: =AVERAGE(verkaeufe!G2:G27) -> 844.42308 | C7: MITTELWERT
A9: Günstigster und teuerster Einzelpreis: | B9: =MIN(verkaeufe!F2:F27) -> 25 | C9: =MAX(verkaeufe!F2:F27) -> 1200 | D9: MIN / MAX
A11: Wie viele Verkäufe wurden erfasst? | B11: =COUNTA(verkaeufe!A2:A27) -> 26 | C11: ANZAHL: zählt Zellen mit numerischen Werten; ANZAHL2: zählt Zellen, die nicht leer sind
A13: Wie oft hat Anna verkauft? | B13: =COUNTIF(verkaeufe!B:B, "Anna") -> 7 | C13: ZÄHLENWENN
A15: Wie viele Computer‑Produkte wurden verkauft? | B15: =SUMIF(verkaeufe!D:D, "Computer", verkaeufe!E:E) -> 26 | C15: SUMMEWENN
A17: Gesamtumsatz von Ben: | B17: =SUMIF(verkaeufe!B:B, "Ben", verkaeufe!G:G) -> 5190 | C17: SUMMEWENN
A19: Umsatz der Kategorie "Computer" von "Clara": | B19: =SUMIFS(verkaeufe!G:G, verkaeufe!D:D, "Computer", verkaeufe!B:B, "Clara") -> 2800 | C19: SUMMEWENNS
A23: 3.2 Nachschlage- und Verweisfunktionen
A25: E-Mail von "David" mit SVERWEIS: | B25: =VLOOKUP("David", mitarbeiter!A:C, 3, FALSE) -> david@firma.at
A27: E-Mail von "David" mit XVERWEIS: | B27: =_xlfn.XLOOKUP("David", mitarbeiter!A:A, mitarbeiter!C:C) -> david@firma.at
A29: Transponiere die Mitarbeiterdaten und wende den WVERWEIS an. | B29: =HLOOKUP("David", mitarbeiter_transponiert!A9:E12, 3, FALSE) -> david@firma.at
A33: 3.3 Logische Funktionen
A35: Markiere Verkäufe über 1.000 €: | B35: Tabellenblatt 'verkaeufe' | C35: ok
A37: Prüfe: Verkäuferin ist Anna und Kategorie ist Computer: | B37: Tabellenblatt 'verkaeufe' | C37: ok
A39: Prüfe: Kategorie ist Computer oder Zubehör: | B39: Tabellenblatt 'verkaeufe' | C39: ok
A41: E-Mail per XVERWEIS + Fehler abfangen: | B41: Tabellenblatt 'verkaeufe' | C41: ok
A45: 3.4 Textfunktionen
A47: Produkt + Kategorie kombinieren: | B47: Tabellenblatt 'verkaeufe' | C47: keine Lösung
A49: VerkäuferIn, Abteilung u. Mail kombinieren (ohne Funktion): | B49: Tabellenblatt 'mitarbeiter' | C49: keine Lösung
A51: EMail-Adresse zerlegen: | B51: Tabellenblatt 'mitarbeiter' | C51: keine Lösung
A53: Erste 3 Buchstaben der Kategorie | B53: Tabellenblatt 'verkaeufe' | C53: keine Lösung
A55: Überflüssige Leerzeichen entfernen | B55: eigenes Beispiel | C55: keine Lösung
A59: 3.5 Datums- und Zeitfunktionen
A61: Heutiges Datum: | B61: =TODAY() -> 46088
A63: Heutiges Datum + Uhrzeit: | B63: =NOW() -> 46088.986
A65: Neue Spalte "Tage seit Verkauf" | B65: Tabellenblatt 'verkaeufe' | C65: ok
A69: Fortgeschritten
A70: Teile den Verkäufern alle Rechnungsnummern ihrer Verkäufe zu (siehe Screenshot)

Sheet verkaeufe
A1: Datum | B1: VerkäuferIn | C1: Produkt | D1: Kategorie | E1: Stück | F1: Einzelpreis | G1: Umsatz | H1: Rechnung | I1: Kommentar | J1: Umsatz >1.000? | K1: Anna + Computer | L1: Kat: Computer ODER Zubehör | M1: Mail | N1: Tage seit Verkauf
A2: 46025 | B2: Anna | C2: Laptop Pro 15 | D2: Computer | E2: 2 | F2: 1200 | G2: 2400 | H2: RE-2026-0001 | I2: Top Kunde | J2: =IF(G2>=1000, "ja", "nein") -> ja | K2: =IF(AND(B2="Anna", D2="Computer"), "ja", "nein") -> ja | L2: =IF(OR(D2="Computer", D2="Zubehör"), "ja", "nein") -> ja | M2: =_xlfn.XLOOKUP(B2, mitarbeiter!A:A, mitarbeiter!C:C, "Keine Adresse gefunden") -> anna@firma.at | N2: =TODAY() - A2 -> 63
A3: 46026 | B3: Ben | C3: Office Chair X | D3: Möbel | E3: 5 | F3: 150 | G3: 750 | H3: RE-2026-0002 | I3: Express Lieferung | J3: =IF(G3>=1000, "ja", "nein") -> nein | K3: =IF(AND(B3="Anna", D3="Computer"), "ja", "nein") -> nein | L3: =IF(OR(D3="Computer", D3="Zubehör"), "ja", "nein") -> nein | M3: =_xlfn.XLOOKUP(B3, mitarbeiter!A:A, mitarbeiter!C:C, "Keine Adresse gefunden") -> ben@firma.at | N3: =TODAY() - A3 -> 62
A4: 46026 | B4: Clara | C4: Monitor 27 UHD | D4: Computer | E4: 3 | F4: 320 | G4: 960 | H4: RE-2026-0003 | I4: Defekt gemeldet | J4: =IF(G4>=1000, "ja", "nein") -> nein | K4: =IF(AND(B4="Anna", D4="Computer"), "ja", "nein") -> nein | L4: =IF(OR(D4="Computer", D4="Zubehör"), "ja", "nein") -> ja | M4: =_xlfn.XLOOKUP(B4, mitarbeiter!A:A, mitarbeiter!C:C, "Keine Adresse gefunden") -> clara@firma.at | N4: =TODAY() - A4 -> 62
A5: 46027 | B5: Anna | C5: Laptop Air 13 | D5: Computer | E5: 1 | F5: 950 | G5: 950 | H5: RE-2026-0004 | I5: VIP | J5: =IF(G5>=1000, "ja", "nein") -> nein | K5: =IF(AND(B5="Anna", D5="Computer"), "ja", "nein") -> ja | L5: =IF(OR(D5="Computer", D5="Zubehör"), "ja", "nein") -> ja | M5: =_xlfn.XLOOKUP(B5, mitarbeiter!A:A, mitarbeiter!C:C, "Keine Adresse gefunden") -> anna@firma.at | N5: =TODAY() - A5 -> 61
A6: 46028 | B6: David | C6: Schreibtisch L | D6: Möbel | E6: 2 | F6: 400 | G6: 800 | H6: RE-2026-0005 | I6: Rückfrage | J6: =IF(G6>=1000, "ja", "nein") -> nein | K6: =IF(AND(B6="Anna", D6="Computer"), "ja", "nein") -> nein | L6: =IF(OR(D6="Computer", D6="Zubehör"), "ja", "nein") -> nein | M6: =_xlfn.XLOOKUP(B6, mitarbeiter!A:A, mitarbeiter!C:C, "Keine Adresse gefunden") -> david@firma.at | N6: =TODAY() - A6 -> 60
A7: 46028 | B7: Ben | C7: Maus Wireless | D7: Zubehör | E7: 10 | F7: 25 | G7: 250 | H7: RE-2026-0006 | I7: Schnell erledigt | J7: =IF(G7>=1000, "ja", "nein") -> nein | K7: =IF(AND(B7="Anna", D7="Computer"), "ja", "nein") -> nein | L7: =IF(OR(D7="Computer", D7="Zubehör"), "ja", "nein") -> ja | M7: =_xlfn.XLOOKUP(B7, mitarbeiter!A:A, mitarbeiter!C:C, "Keine Adresse gefunden") -> ben@firma.at | N7: =TODAY() - A7 -> 60
A8: 46029 | B8: Clara | C8: Tastatur MX | D8: Zubehör | E8: 4 | F8: 80 | G8: 320 | H8: RE-2026-0007 | I8: Kunde zufrieden | J8: =IF(G8>=1000, "ja", "nein") -> nein | K8: =IF(AND(B8="Anna", D8="Computer"), "ja", "nein") -> nein | L8: =IF(OR(D8="Computer", D8="Zubehör"), "ja", "nein") -> ja | M8: =_xlfn.XLOOKUP(B8, mitarbeiter!A:A, mitarbeiter!C:C, "Keine Adresse gefunden") -> clara@firma.at | N8: =TODAY() - A8 -> 59
A9: 46029 | B9: Anna | C9: Docking Station Z | D9: Zubehör | E9: 3 | F9: 140 | G9: 420 | H9: RE-2026-0008 | I9: Wiederholungskauf | J9: =IF(G9>=1000, "ja", "nein") -> nein | K9: =IF(AND(B9="Anna", D9="Computer"), "ja", "nein") -> nein | L9: =IF(OR(D9="Computer", D9="Zubehör"), "ja", "nein") -> ja | M9: =_xlfn.XLOOKUP(B9, mitarbeiter!A:A, mitarbeiter!C:C, "Keine Adresse gefunden") -> anna@firma.at | N9: =TODAY() - A9 -> 59
A10: 46030 | B10: David | C10: Laptop Pro 15 | D10: Computer | E10: 1 | F10: 1200 | G10: 1200 | H10: RE-2026-0009 | I10: Großauftrag | J10: =IF(G10>=1000, "ja", "nein") -> ja | K10: =IF(AND(B10="Anna", D10="Computer"), "ja", "nein") -> nein | L10: =IF(OR(D10="Computer", D10="Zubehör"), "ja", "nein") -> ja | M10: =_xlfn.XLOOKUP(B10, mitarbeiter!A:A, mitarbeiter!C:C, "Keine Adresse gefunden") -> david@firma.at | N10: =TODAY() - A10 -> 58
A11: 46030 | B11: Ben | C11: Monitor 24 FHD | D11: Computer | E11: 6 | F11: 180 | G11: 1080 | H11: RE-2026-0010 | I11: Rabatt gewährt | J11: =IF(G11>=1000, "ja", "nein") -> ja | K11: =IF(AND(B11="Anna", D11="Computer"), "ja", "nein") -> nein | L11: =IF(OR(D11="Computer", D11="Zubehör"), "ja", "nein") -> ja | M11: =_xlfn.XLOOKUP(B11, mitarbeiter!A:A, mitarbeiter!C:C, "Keine Adresse gefunden") -> ben@firma.at | N11: =TODAY() - A11 -> 58
A12: 46031 | B12: Clara | C12: Office Chair X | D12: Möbel | E12: 2 | F12: 150 | G12: 300 | H12: RE-2026-0011 | I12: Express | J12: =IF(G12>=1000, "ja", "nein") -> nein | K12: =IF(AND(B12="Anna", D12="Computer"), "ja", "nein") -> nein | L12: =IF(OR(D12="Computer", D12="Zubehör"), "ja", "nein") -> nein | M12: =_xlfn.XLOOKUP(B12, mitarbeiter!A:A, mitarbeiter!C:C, "Keine Adresse gefunden") -> clara@firma.at | N12: =TODAY() - A12 -> 57
A13: 46031 | B13: Anna | C13: Maus Wireless | D13: Zubehör | E13: 15 | F13: 25 | G13: 375 | H13: RE-2026-0012 | I13: Lagerabverkauf | J13: =IF(G13>=1000, "ja", "nein") -> nein | K13: =IF(AND(B13="Anna", D13="Computer"), "ja", "nein") -> nein | L13: =IF(OR(D13="Computer", D13="Zubehör"), "ja", "nein") -> ja | M13: =_xlfn.XLOOKUP(B13, mitarbeiter!A:A, mitarbeiter!C:C, "Keine Adresse gefunden") -> anna@firma.at | N13: =TODAY() - A13 -> 57
... A27: 46038 | B27: Ben | C27: Office Chair X | D27: Möbel | E27: 8 | F27: 150 | G27: 1200 | H27: RE-2026-0026 | I27: Express | J27: =IF(G27>=1000, "ja", "nein") -> ja | K27: =IF(AND(B27="Anna", D27="Computer"), "ja", "nein") -> nein | L27: =IF(OR(D27="Computer", D27="Zubehör"), "ja", "nein") -> nein | M27: =_xlfn.XLOOKUP(B27, mitarbeiter!A:A, mitarbeiter!C:C, "Keine Adresse gefunden") -> ben@firma.at | N27: =TODAY() - A27 -> 50

Sheet mitarbeiter
A1: VerkäuferIn | B1: Abteilung | C1: E-Mail | D1: Kürzel | E1: Rechnungen
A2: Anna | B2: Sales | C2: anna@firma.at | D2: AN | E2: {=_xlfn.TEXTJOIN(", ", TRUE, IF(verkaeufe!B:B=mitarbeiter!A2, verkaeufe!H:H, ""))} -> RE-2026-0001, RE-2026-0004, RE-2026-0008, RE-2026-0012, RE-2026-0016, RE-2026-0020, RE-2026-0024
A3: Ben | B3: Sales | C3: ben@firma.at | D3: BE | E3: {=_xlfn.TEXTJOIN(", ", TRUE, IF(verkaeufe!B:B=mitarbeiter!A3, verkaeufe!H:H, ""))} -> RE-2026-0002, RE-2026-0006, RE-2026-0010, RE-2026-0014, RE-2026-0018, RE-2026-0022, RE-2026-0026
A4: Clara | B4: Support | C4: clara@firma.at | D4: CL | E4: {=_xlfn.TEXTJOIN(", ", TRUE, IF(verkaeufe!B:B=mitarbeiter!A4, verkaeufe!H:H, ""))} -> RE-2026-0003, RE-2026-0007, RE-2026-0011, RE-2026-0015, RE-2026-0019, RE-2026-0023
A5: David | B5: Sales | C5: david@firma.at | D5: DA | E5: {=_xlfn.TEXTJOIN(", ", TRUE, IF(verkaeufe!B:B=mitarbeiter!A5, verkaeufe!H:H, ""))} -> RE-2026-0005, RE-2026-0009, RE-2026-0013, RE-2026-0017, RE-2026-0021, RE-2026-0025

Sheet mitarbeiter_transponiert
A1: VerkäuferIn | B1: Abteilung | C1: E-Mail | D1: Kürzel
A2: Anna | B2: Sales | C2: anna@firma.at | D2: AN
A3: Ben | B3: Sales | C3: ben@firma.at | D3: BE
A4: Clara | B4: Support | C4: clara@firma.at | D4: CL | H4: Für das Transponieren der Mitarbeiter:
A5: David | B5: Sales | C5: david@firma.at | D5: DA | H5: - Ursprüngliche Tabelle kopieren
H6: - Rechte Maustaste - Inhalte einfügen - Inhalte einfügen
H7: - Werte + Transponieren
A9: VerkäuferIn | B9: Anna | C9: Ben | D9: Clara | E9: David
A10: Abteilung | B10: Sales | C10: Sales | D10: Support | E10: Sales
A11: E-Mail | B11: anna@firma.at | C11: ben@firma.at | D11: clara@firma.at | E11: david@firma.at
A12: Kürzel | B12: AN | C12: BE | D12: CL | E12: DA
